dittostore/__init__.py
dittostore/dittostore.py
dittostore/objects.py
dittostore-0.0.8.dist-info/METADATA
dittostore-0.0.8.dist-info/RECORD
dittostore-0.0.8.dist-info/WHEEL
dittostore-0.0.8.dist-info/top_level.txt
