Metadata-Version: 2.1
Name: dittostore
Version: 0.0.8
Summary: Simple and easy to use ODM for Google Datastore
Home-page: https://github.com/OrbitalAds/dittostore
Author: OrbitalAds
Author-email: dev@orbitalads.io
License: UNKNOWN
Keywords: object document mapping odm datastore google google-cloud google-datastore
Platform: UNKNOWN
Classifier: Development Status :: 3 - Alpha
Classifier: Intended Audience :: Developers
Classifier: Topic :: Software Development :: Libraries :: Python Modules
Classifier: License :: OSI Approved :: GNU General Public License v3 (GPLv3)
Classifier: Natural Language :: Spanish
Classifier: Programming Language :: Python :: 3.6
Classifier: Programming Language :: Python :: 3.7
Requires-Dist: google-cloud-datastore
